.travis.yml
license.txt
readme.md
requirements.txt
setup.cfg
setup.py
tox.ini
file_sync_s3.egg-info/PKG-INFO
file_sync_s3.egg-info/SOURCES.txt
file_sync_s3.egg-info/dependency_links.txt
file_sync_s3.egg-info/entry_points.txt
file_sync_s3.egg-info/not-zip-safe
file_sync_s3.egg-info/pbr.json
file_sync_s3.egg-info/requires.txt
file_sync_s3.egg-info/top_level.txt
src/readme.md
src/main/readme.md
src/main/file_sync_s3/__init__.py
src/main/file_sync_s3/aws_s3.py
src/main/file_sync_s3/config.py
src/main/file_sync_s3/logster.py
src/main/file_sync_s3/service.py
src/main/file_sync_s3/setup.py
src/main/file_sync_s3/watcher.py
src/main/file_sync_s3/etc/readme.md
src/main/file_sync_s3/etc/file_sync_s3/arkon.ini
src/main/file_sync_s3/etc/init.d/file_sync_s3
src/main/file_sync_s3/etc/init.d/readme.md
src/main/file_sync_s3/etc/systemd/readme.md
src/main/file_sync_s3/etc/systemd/system/file_sync_s3.service
src/test/readme.md
src/test/file_sync_s3_test/.gitignore
src/test/file_sync_s3_test/__init__.py
src/test/file_sync_s3_test/aws_s3_test.py
src/test/file_sync_s3_test/config_test.py
src/test/file_sync_s3_test/logster_test.py
src/test/file_sync_s3_test/service_main.py
src/test/file_sync_s3_test/service_test.py
src/test/file_sync_s3_test/setup_main.py
src/test/file_sync_s3_test/setup_test.py
src/test/file_sync_s3_test/watcher_main.py
src/test/file_sync_s3_test/watcher_test.py
src/verify/readme.md
src/verify/library/__init__.py
tool/github_squash.py
tool/install_local.py
tool/perform_tox.py
tool/provision_env.sh
tool/readme.md
tool/release_update.py