Metadata-Version: 2.1
Name: file-sync-s3
Version: 0.2.4.dev1
Summary: Amazon AWS S3 file sync service with inotify watchdog and scheduled expiration
Home-page: https://github.com/random-python/file_sync_s3
Author: Andrei Pozolotin
Author-email: andrei.pozolotin@gmail.com
License: Apache-2
Keywords: openrc,systemd,service,inotify,expire,file,sync,amazon,aws,s3
Platform: UNKNOWN
Classifier: Development Status :: 4 - Beta
Classifier: Environment :: Console
Classifier: Intended Audience :: Developers
Classifier: Intended Audience :: Information Technology
Classifier: Intended Audience :: System Administrators
Classifier: License :: OSI Approved :: Apache Software License
Classifier: Operating System :: POSIX :: Linux
Classifier: Programming Language :: Python
Classifier: Programming Language :: Python :: 3.8
Classifier: Topic :: System :: Systems Administration
Classifier: Topic :: Terminals
Classifier: Topic :: Utilities
